docnado/__init__.py
docnado/docnado.py
docnado/logo.png
docnado/navtree.py
docnado/docs/home.md
docnado/docs/contributing/development.md
docnado/docs/documents/blue_paragraph.html
docnado/docs/documents/callouts.md
docnado/docs/documents/code.md
docnado/docs/documents/custom.css.html
docnado/docs/documents/custom_text_box.html
docnado/docs/documents/html.md
docnado/docs/documents/images.md
docnado/docs/documents/links.md
docnado/docs/documents/lists.md
docnado/docs/documents/markdown.md
docnado/docs/documents/pdf.md
docnado/docs/documents/tables.md
docnado/docs/documents/text.md
docnado/docs/documents/text_input.html
docnado/docs/documents/videos.md
docnado/docs/documents/assets/big_buck_bunny.ogv
docnado/docs/documents/assets/example.csv
docnado/docs/documents/assets/example.pdf
docnado/docs/documents/assets/logo.png
docnado/docs/documents/assets/relative_link.md
docnado/docs/setup/installation.md
docnado/docs/setup/meta-data.md
docnado/docs/setup/new_project.md
docnado/docs/setup/new_template.md
docnado/docs/setup/project_structure.md
docnado/docs/setup/assets/new_template-b653cfa0.png
docnado/docs/tooling/broken_links.md
docnado/docs/tooling/command_line.md
docnado/docs/tooling/env_variables.md
docnado/docs/tooling/exporting_to_pdf.md
docnado/docs/tooling/extra_tips.md
docnado/docs/tooling/proselint.md
docnado/docs/tooling/unused_assets.md
docnado/style/lib/bootbox-4.4.0.min.js
docnado/style/lib/bootstrap-4.0.0.min.css
docnado/style/lib/bootstrap-4.0.0.min.js
docnado/style/lib/font-awesome-4.7.0.min.css
docnado/style/lib/highlight-9.12.0.min.js
docnado/style/lib/highlightjs-9.12.0.min.css
docnado/style/lib/jquery-3.2.1.slim.min.js
docnado/style/static/default.css
docnado/style/static/default.scss
docnado/style/static/fonts/FontAwesome.otf
docnado/style/static/fonts/fontawesome-webfont.eot
docnado/style/static/fonts/fontawesome-webfont.svg
docnado/style/static/fonts/fontawesome-webfont.ttf
docnado/style/static/fonts/fontawesome-webfont.woff
docnado-1.0.13.dist-info/LICENSE
docnado-1.0.13.dist-info/METADATA
docnado-1.0.13.dist-info/WHEEL
docnado-1.0.13.dist-info/entry_points.txt
docnado-1.0.13.dist-info/top_level.txt
docnado-1.0.13.dist-info/RECORD
