Metadata-Version: 2.1
Name: docnado
Version: 1.0.13
Summary: A rapid documentation tool to blow you away.
Home-page: https://github.com/HEInventions/docnado
Author: Hardy & Ellis Inventions LTD
Author-email: support@heinventions.com
License: UNKNOWN
Platform: UNKNOWN
Classifier: Programming Language :: Python :: 3
Classifier: License :: OSI Approved :: MIT License
Requires-Python: >=3.6.0
License-File: LICENSE
Requires-Dist: Flask (==1.1.4)
Requires-Dist: Markdown (==2.6.11)
Requires-Dist: Frozen-Flask (==0.15)
Requires-Dist: beautifulsoup4 (==4.9.0)
Requires-Dist: requests (==2.23.0)
Requires-Dist: watchdog (==0.10.2)
Requires-Dist: markupsafe (==2.0.1)
